carburetor/__init__.py
carburetor/actions.py
carburetor/carburetor.py
carburetor/config.py
carburetor/handler.py
carburetor/res.gresource
carburetor/ui.py
carburetor/locales/de/LC_MESSAGES/carburetor.mo
carburetor/locales/el/LC_MESSAGES/carburetor.mo
carburetor/locales/es/LC_MESSAGES/carburetor.mo
carburetor/locales/fa/LC_MESSAGES/carburetor.mo
carburetor/locales/fi/LC_MESSAGES/carburetor.mo
carburetor/locales/fr/LC_MESSAGES/carburetor.mo
carburetor/locales/hi/LC_MESSAGES/carburetor.mo
carburetor/locales/hr/LC_MESSAGES/carburetor.mo
carburetor/locales/it/LC_MESSAGES/carburetor.mo
carburetor/locales/ja/LC_MESSAGES/carburetor.mo
carburetor/locales/nb_NO/LC_MESSAGES/carburetor.mo
carburetor/locales/nl/LC_MESSAGES/carburetor.mo
carburetor/locales/pl/LC_MESSAGES/carburetor.mo
carburetor/locales/pt/LC_MESSAGES/carburetor.mo
carburetor/locales/pt_BR/LC_MESSAGES/carburetor.mo
carburetor/locales/ru/LC_MESSAGES/carburetor.mo
carburetor/locales/sv/LC_MESSAGES/carburetor.mo
carburetor/locales/tr/LC_MESSAGES/carburetor.mo
carburetor/locales/zh_Hans/LC_MESSAGES/carburetor.mo
carburetor-4.5.1.dist-info/entry_points.txt
carburetor-4.5.1.dist-info/LICENSE
carburetor-4.5.1.dist-info/WHEEL
carburetor-4.5.1.dist-info/METADATA
carburetor-4.5.1.dist-info/RECORD
