Metadata-Version: 2.1
Name: carburetor
Version: 4.5.1
Summary: GTK frontend for Tractor
Keywords: Tor,onion,stem
Author-email: Danial Behzadi <dani.behzi@ubuntu.com>
Requires-Python: >=3.9
Classifier: Programming Language :: Python :: 3
Classifier: License :: OSI Approved :: GNU General Public License v3 or later (GPLv3+)
Classifier: Operating System :: OS Independent
Requires-Dist: traxtor
Project-URL: Bug Tracker, https://framagit.org/tractor/carburetor/issues
Project-URL: Documentation, https://framagit.org/tractor/carburetor/raw/main/data/carburetor.1
Project-URL: Homepage, https://tractor.frama.io/carburetor
Project-URL: Source Code, https://framagit.org/tractor/carburetor
